Metadata-Version: 2.1
Name: neseg
Version: 0.7
Summary: 机构名称分割
Home-page: https://github.com/huhongjun/neseg
Author: pastoral
Author-email: huhongjun@gmail.com
License: Apache License 2.0
Keywords: corpus,NLP
Platform: UNKNOWN
Classifier: Intended Audience :: Developers
Classifier: Natural Language :: Chinese (Simplified)
Classifier: Natural Language :: Chinese (Traditional)
Classifier: Operating System :: OS Independent
Classifier: Programming Language :: Python
Classifier: Programming Language :: Python :: 2
Classifier: Programming Language :: Python :: 2.7
Classifier: Programming Language :: Python :: 3
Classifier: Topic :: Text Processing
Classifier: Topic :: Text Processing :: Indexing
Classifier: Topic :: Text Processing :: Linguistic
